LICENSE
MANIFEST.in
README.md
requirements.txt
setup.py
crowdin/__init__.py
crowdin/cli.py
crowdin/connection.py
crowdin/methods.py
crowdin/locales/en/LC_MESSAGES/cli.mo
crowdin_cli_py.egg-info/PKG-INFO
crowdin_cli_py.egg-info/SOURCES.txt
crowdin_cli_py.egg-info/dependency_links.txt
crowdin_cli_py.egg-info/entry_points.txt
crowdin_cli_py.egg-info/not-zip-safe
crowdin_cli_py.egg-info/requires.txt
crowdin_cli_py.egg-info/top_level.txt